pandas_tosql_dbx_fix/__init__.py
pandas_tosql_dbx_fix/main.py
pandas_tosql_dbx_fix-1.0.2.dist-info/licenses/LICENSE
pandas_tosql_dbx_fix-1.0.2.dist-info/WHEEL
pandas_tosql_dbx_fix-1.0.2.dist-info/entry_points.txt
pandas_tosql_dbx_fix-1.0.2.dist-info/METADATA
pandas_tosql_dbx_fix-1.0.2.dist-info/RECORD
