Metadata-Version: 2.4
Name: pandas-tosql-dbx-fix
Version: 1.0.2
Summary: Fix for the Pandas to_sql() dataframe method that fails when we try pushing more than 256 values.
Author: Tarek Samhan
Author-email: Tarek Samhan <tsamhan@gmail.com>
License-Expression: MIT
License-File: LICENSE
Requires-Dist: databricks-sqlalchemy>=2.0.8
Requires-Dist: pandas>=2.3.3
Requires-Dist: sqlalchemy>=2.0.45
Requires-Python: >=3.10
Project-URL: Homepage, https://github.com/beefupinetree/pandas-tosql-dbx-fix
